pywhlobf/__init__.py
pywhlobf/code_file_processor.py
pywhlobf/command_line_interface.py
pywhlobf/execution_context.py
pywhlobf/package_folder_processor.py
pywhlobf/wheel_file_processor.py
pywhlobf/component/__init__.py
pywhlobf/component/cpp_compiler.py
pywhlobf/component/cpp_generator.py
pywhlobf/component/flag_setter.py
pywhlobf/component/source_code_injector.py
pywhlobf/component/string_literal_obfuscator.py
pywhlobf/component/string_literal_obfuscator_asset/obfuscate.h
pywhlobf-23.1.0.dist-info/LICENSE
pywhlobf-23.1.0.dist-info/METADATA
pywhlobf-23.1.0.dist-info/WHEEL
pywhlobf-23.1.0.dist-info/entry_points.txt
pywhlobf-23.1.0.dist-info/top_level.txt
pywhlobf-23.1.0.dist-info/RECORD
